pixelgen/core.py
pixelgen/preview.py
pixelgen/tools.py
pixelgen-0.0.8.dist-info/METADATA
pixelgen-0.0.8.dist-info/WHEEL
pixelgen-0.0.8.dist-info/top_level.txt
pixelgen-0.0.8.dist-info/RECORD
