Metadata-Version: 2.4
Name: pixelgen
Version: 0.0.8
Summary: Pixel Generator
Author-email: rifqanzalbina <zalbinarifqan19@gmail.com>
License: MIT
Project-URL: Homepage, https://github.com/rifqanzalbina/product-generator
Project-URL: Bug Tracker, https://github.com/rifqanzalbina/product-generator/issues
Classifier: Programming Language :: Python :: 3
Classifier: License :: OSI Approved :: MIT License
Classifier: Operating System :: OS Independent
Classifier: Natural Language :: Indonesian
Classifier: Topic :: Text Processing :: Linguistic
Requires-Python: >=3.6
Requires-Dist: Pillow>=5.2.0
Requires-Dist: numpy>=1.0.0
